tap2shex/__init__.py
tap2shex/cli.py
tap2shex/defaults.py
tap2shex/mkshex.py
tap2shex/utils.py
tap2shex-0.2.dist-info/entry_points.txt
tap2shex-0.2.dist-info/WHEEL
tap2shex-0.2.dist-info/METADATA
tap2shex-0.2.dist-info/RECORD
